[{"problemid":1301,"first":"Black to Move","type":"Mate in Two","fen":"2k5/ppp1r1pp/8/4n3/8/5P1b/2Q1PP1P/6KR b - - 0 1","solutions":{"e5f3":["e2f3","e7e1"]}},{"problemid":1302,"first":"Black to Move","type":"Mate in Two","fen":"8/1Qpk1pp1/7p/4qP2/1P5r/2P4P/3r2P1/R4R1K b - - 0 1","solutions":{"h4h3":["h1g1","e5h2"]}},{"problemid":1303,"first":"Black to Move","type":"Mate in Two","fen":"6k1/3Q2p1/3n4/4p3/8/2Pq2P1/PP1Nbr2/R1K5 b - - 0 1","solutions":{"f2f1":["d2f1","d3d1"]}},{"problemid":1304,"first":"Black to Move","type":"Mate in Two","fen":"3r2k1/1b3ppp/pb2p3/1p6/1P2PPnq/P2N2P1/1B2Q2P/2RR3K b - - 0 1","solutions":{"b7e4":["e2e4","h4h2"]}},{"problemid":1305,"first":"Black to Move","type":"Mate in Two","fen":"3RQ3/p4pk1/1p4p1/2q3Pp/6bK/P1r5/6PP/3n3R b - - 0 1","solutions":{"c3h3":["g2h3","c5f2"]}},{"problemid":1306,"first":"Black to Move","type":"Mate in Two","fen":"2r2qk1/p3p1bR/3p4/1b1P2Q1/1p4P1/1N2BP2/Pr6/K6R b - - 0 1","solutions":{"b2b1":["a1b1","b5d3"]}},{"problemid":1307,"first":"Black to Move","type":"Mate in Two","fen":"8/6p1/6k1/R2pp1p1/2rPn1P1/1p1KP3/1Pr1R3/3N4 b - - 0 1","solutions":{"e4c5":["a5c5","e5e4"]}},{"problemid":1308,"first":"Black to Move","type":"Mate in Two","fen":"5r2/4k1r1/3N4/1QpPp2n/pp2P3/5PPK/PP6/2R3R1 b - - 0 1","solutions":{"h5f4":["g3f4","f8h8"]}},{"problemid":1309,"first":"Black to Move","type":"Mate in Two","fen":"7k/p7/1p6/2p1b2p/4PN1P/2P1KR2/PP1r1R2/3r4 b - - 0 1","solutions":{"e5d4":["c3d4","c5d4"]}},{"problemid":1310,"first":"Black to Move","type":"Mate in Two","fen":"b5k1/1q3ppp/2r2n2/R4NB1/3b4/4N3/1P4PP/Q5K1 b - - 0 1","solutions":{"c6c1":["a1c1","b7g2"]}},{"problemid":1311,"first":"Black to Move","type":"Mate in Two","fen":"8/1p1P2bk/p5pp/3Q1pq1/P3r3/5pB1/1P5K/R4R2 b - - 0 1","solutions":{"e4h4":["g3h4","g5g2"]}},{"problemid":1312,"first":"Black to Move","type":"Mate in Two","fen":"2krr3/ppb2Qpp/8/1PPN4/5pnP/B2q1Nn1/P5P1/R5KR b - - 0 1","solutions":{"d3f1":["a1f1","g3e2"]}},{"problemid":1313,"first":"Black to Move","type":"Mate in Two","fen":"6k1/p4pp1/1p5p/5N1q/8/QP3n1P/P1r3P1/3R3K b - - 0 1","solutions":{"h5h3":["g2h3","c2h2"]}},{"problemid":1314,"first":"Black to Move","type":"Mate in Two","fen":"7k/7p/7N/8/2Qn4/6pb/6rR/5K1R b - - 0 1","solutions":{"g2g1":["f1g1","d4f3"]}},{"problemid":1315,"first":"Black to Move","type":"Mate in Two","fen":"8/p1k5/B1p5/2Pp1p2/P2Pb2p/6r1/3Q1RPK/1r6 b - - 0 1","solutions":{"g3h3":["g2h3","b1h1"]}},{"problemid":1316,"first":"Black to Move","type":"Mate in Two","fen":"2k5/2p3pp/ppb3r1/4Pp1n/PP3P2/2N1B3/6RP/6RK b - - 0 1","solutions":{"h5g3":["h2g3","g6h6"]}},{"problemid":1317,"first":"Black to Move","type":"Mate in Two","fen":"r4rk1/ppq2ppp/2p2B2/2b1n3/4P1N1/P1N4P/BP1Q1PP1/5RKR b - - 0 1","solutions":{"e5f3":["g2f3","c7g3"]}},{"problemid":1318,"first":"Black to Move","type":"Mate in Two","fen":"5k2/6pp/1q5r/p2RPp2/2B1nP2/2P4P/2P3PK/2Q4R b - - 0 1","solutions":{"h6h3":["g2h3","b6f2"]}},{"problemid":1319,"first":"Black to Move","type":"Mate in Two","fen":"8/3r1pk1/1Q5p/1pp3p1/2Bn1Pb1/2P5/PPR3PP/1NKR4 b - - 0 1","solutions":{"d4b3":["a2b3","d7d1"]}},{"problemid":1320,"first":"Black to Move","type":"Mate in Two","fen":"4k2r/4r1p1/8/8/1b1R3p/4nR1P/1N3KP1/5BN1 b k - 0 1","solutions":{"e3g4":["h3g4","b4e1"]}},{"problemid":1321,"first":"Black to Move","type":"Mate in Two","fen":"7k/6b1/4p2p/8/5nPP/1p2KP2/1Pr5/1RR5 b - - 0 1","solutions":{"c2e2":["e3f4","g7e5"]}},{"problemid":1322,"first":"Black to Move","type":"Mate in Two","fen":"4k3/3p1pp1/p2Pp3/1pr2n2/5P2/1PP2qPK/P2B4/5RQ1 b - - 0 1","solutions":{"f5e3":["g1e3","c5h5"]}},{"problemid":1323,"first":"Black to Move","type":"Mate in Two","fen":"2k1r3/2pp1PR1/1p6/8/1p1n4/3P4/2P2Q2/1qBK4 b - - 0 1","solutions":{"e8e1":["f2e1","b1c2"]}},{"problemid":1324,"first":"Black to Move","type":"Mate in Two","fen":"4k3/p4p1p/3p1p2/2p1r3/2P1r1P1/P7/1P1QnPP1/3R1R1K b - - 0 1","solutions":{"e5h5":["g4h5","e4h4"]}},{"problemid":1325,"first":"Black to Move","type":"Mate in Two","fen":"r2qk2r/ppp5/3p1n2/2b1p3/2B1P1b1/3P2pP/PPPQnPP1/RN3R1K b kq - 0 1","solutions":{"h8h3":["g2h3","g4f3"]}},{"problemid":1326,"first":"Black to Move","type":"Mate in Two","fen":"4k2r/3r1p2/6p1/1pb1Pn2/p1p1QP1p/3P4/PP4PP/1RBR3K b k - 0 1","solutions":{"f5g3":["h2g3","h4g3"]}},{"problemid":1327,"first":"Black to Move","type":"Mate in Two","fen":"6k1/ppq3pp/2p3p1/3p4/6P1/2NB3P/PPPQR1Kb/R4r2 b - - 0 1","solutions":{"c7g3":["g2f1","g3g1"]}},{"problemid":1328,"first":"Black to Move","type":"Mate in Two","fen":"6k1/6p1/p3p1Kp/P3p3/4Pr2/2P1N3/1P2nPPN/R5R1 b - - 0 1","solutions":{"f4f5":["e4f5","e2f4"]}},{"problemid":1329,"first":"Black to Move","type":"Mate in Two","fen":"r3k1r1/pp1n1p2/2pbp2p/1P1p4/3P1q2/P1N2P2/2P1B1NP/R2Q1RK1 b q - 0 1","solutions":{"g8g2":["g1g2","f4h2"]}},{"problemid":1330,"first":"Black to Move","type":"Mate in Two","fen":"8/pkp5/3p1P2/2p5/1p6/3P3P/2P1rP2/qQKR3R b - - 0 1","solutions":{"e2c2":["c1c2","a1c3"]}},{"problemid":1331,"first":"Black to Move","type":"Mate in Two","fen":"r1b2rk1/1p6/5qp1/3pBn2/p7/P2B2P1/1PQ1NPK1/R6R b - - 0 1","solutions":{"f5e3":["f2e3","f6f2"]}},{"problemid":1332,"first":"Black to Move","type":"Mate in Two","fen":"r5k1/1npb4/1p3qrp/2pP1P2/1PP1pP2/pKN1B2P/Pb1QB1R1/6R1 b - - 0 1","solutions":{"f6c3":["d2c3","d7a4"]}},{"problemid":1333,"first":"Black to Move","type":"Mate in Two","fen":"2k3rr/8/6q1/8/5Q2/4N3/5P1p/R4R1K b - - 0 1","solutions":{"g6g1":["f1g1","h2g1r"]}},{"problemid":1334,"first":"Black to Move","type":"Mate in Two","fen":"4rk2/1p3p1p/p4p2/8/1bPn1Q2/1P1P4/q2N2PP/2RKBB1R b - - 0 1","solutions":{"a2b3":["d2b3","e8e1"]}},{"problemid":1335,"first":"Black to Move","type":"Mate in Two","fen":"Q1b1r1k1/4q1p1/2p4p/3n1p1B/1rn5/2NP4/PPP2bPP/RNBK3R b - - 0 1","solutions":{"e7e1":["h1e1","e8e1"]}},{"problemid":1336,"first":"Black to Move","type":"Mate in Two","fen":"5r1k/R5pp/8/3P1q2/2P5/BPQ2BP1/P4nK1/4r3 b - - 0 1","solutions":{"f5h3":["g2f2","h3f1"]}},{"problemid":1337,"first":"Black to Move","type":"Mate in Two","fen":"r1b2rk1/pp3p1p/3p2p1/2pPp3/2PbPPnq/3B3P/PPQ3P1/R1BN1R1K b - - 0 1","solutions":{"h4g3":["h3g4","g3h4"]}},{"problemid":1338,"first":"Black to Move","type":"Mate in Two","fen":"8/2q2rbk/4b1p1/7p/3pB2P/Q2Pn1P1/4P2K/R3N2R b - - 0 1","solutions":{"c7g3":["h2g3","g7e5"]}},{"problemid":1339,"first":"Black to Move","type":"Mate in Two","fen":"6k1/P6p/6p1/3p4/R3b3/8/2q3PP/3rQB1K b - - 0 1","solutions":{"c2g2":["f1g2","d1e1"]}},{"problemid":1340,"first":"Black to Move","type":"Mate in Two","fen":"r3r1k1/1p3p2/p7/3P1Q2/P4Pnp/5B2/1P3NPq/R1B2K2 b - - 0 1","solutions":{"h2g1":["f1g1","e8e1"]}},{"problemid":1341,"first":"Black to Move","type":"Mate in Two","fen":"2k5/R1p3bp/1q6/3ppr2/Qp6/1p1PP3/1P1KP2P/2R5 b - - 0 1","solutions":{"b6e3":["d2e3","g7h6"]}},{"problemid":1342,"first":"Black to Move","type":"Mate in Two","fen":"3b4/1b4k1/1p6/1P3ppQ/3p2p1/1q4P1/3P1N1K/7R b - - 0 1","solutions":{"b3g3":["h2g3","d8c7"]}},{"problemid":1343,"first":"Black to Move","type":"Mate in Two","fen":"4r1k1/q4p2/8/8/4n1P1/P6p/Q1P5/R3BKR1 b - - 0 1","solutions":{"a7f2":["e1f2","e4d2"]}},{"problemid":1344,"first":"Black to Move","type":"Mate in Two","fen":"b1r1r1k1/6pp/p2b4/1pq2pBQ/1n3P2/2N3P1/PPP2P2/R4BKR b - - 0 1","solutions":{"c5f2":["g1f2","d6c5"]}},{"problemid":1345,"first":"Black to Move","type":"Mate in Two","fen":"5rk1/p1b3qp/1p2Np2/5Q2/5B1p/4P2P/PP3nPK/6R1 b - - 0 1","solutions":{"g7g3":["f4g3","c7g3"]}},{"problemid":1346,"first":"Black to Move","type":"Mate in Two","fen":"r5k1/6pp/8/2N1p2P/3nP3/6Q1/pPq2PB1/K1R1R3 b - - 0 1","solutions":{"c2b1":["c1b1","d4c2"]}},{"problemid":1347,"first":"Black to Move","type":"Mate in Two","fen":"7k/2R5/3r3q/1Q1Pp1r1/4N3/5P2/7P/6RK b - - 0 1","solutions":{"h6h2":["h1h2","d6h6"]}},{"problemid":1348,"first":"Black to Move","type":"Mate in Two","fen":"r3k2r/pp2b2p/3pQ3/8/4n3/3N4/PBPPPqnP/1RNK1B1R b kq - 0 1","solutions":{"f2e1":["d3e1","e4f2"]}},{"problemid":1349,"first":"Black to Move","type":"Mate in Two","fen":"7Q/4kbQ1/5p2/4pK2/4P3/3p1P2/8/6q1 b - - 0 1","solutions":{"g1g6":["g7g6","f7e6"]}},{"problemid":1350,"first":"Black to Move","type":"Mate in Two","fen":"r1b1k2r/bppp1ppp/p7/8/B3P1n1/5N2/PP3qPP/RNBQR2K b kq - 0 1","solutions":{"f2g1":["e1g1","g4f2"]}},{"problemid":1351,"first":"Black to Move","type":"Mate in Two","fen":"r6k/pp4pp/2n5/2b1p1BQ/2Pq4/2N5/PP3rPP/1BR1R1K1 b - - 0 1","solutions":{"f2f1":["g1f1","d4f2"]}},{"problemid":1352,"first":"Black to Move","type":"Mate in Two","fen":"3b2k1/1p3pp1/3Bb3/pP1pp2p/P1q5/2N1P1P1/1Q3PKP/8 b - - 0 1","solutions":{"e6h3":["g2h3","c4f1"]}},{"problemid":1353,"first":"Black to Move","type":"Mate in Two","fen":"5rk1/R6p/8/3R1q2/2P4K/BPQ2BP1/P4n2/4r3 b - - 0 1","solutions":{"e1h1":["f3h1","f5g4"]}},{"problemid":1354,"first":"Black to Move","type":"Mate in Two","fen":"3rkb2/ppp1q2p/6N1/7Q/4n3/8/PPn2PPP/RNBB1K1R b - - 0 1","solutions":{"e4g3":["h2g3","e7e1"]}},{"problemid":1355,"first":"Black to Move","type":"Mate in Two","fen":"1R6/1R6/7p/1p3npk/5p2/B1r4P/5PPK/4r3 b - - 0 1","solutions":{"f5g3":["f2g3","f4g3"]}},{"problemid":1356,"first":"Black to Move","type":"Mate in Two","fen":"6k1/5ppp/8/7N/3n2Q1/P3r3/KPq5/R6R b - - 0 1","solutions":{"e3a3":["a2a3","c2b3"]}},{"problemid":1357,"first":"Black to Move","type":"Mate in Two","fen":"r1b1k2r/p4pp1/2p4p/n7/3P2n1/2N3q1/PPPKB1PN/2BQ3R b kq - 0 1","solutions":{"a5c4":["e2c4","g3e3"]}},{"problemid":1358,"first":"Black to Move","type":"Mate in Two","fen":"2r3kb/p2bBp2/3R2P1/8/r3P3/1N3P2/1pP4Q/1K5R b - - 0 1","solutions":{"a4a1":["b3a1","b2a1r"]}},{"problemid":1359,"first":"Black to Move","type":"Mate in Two","fen":"Q7/2pk1p1p/pb1pb3/2p5/4n3/3K3P/PP3qP1/RN5R b - - 0 1","solutions":{"c5c4":["d3e4","f2e3"]}},{"problemid":1360,"first":"Black to Move","type":"Mate in Two","fen":"6k1/Q7/5Pr1/4N3/3n4/4R1Pq/5N2/6K1 b - - 0 1","solutions":{"d4e2":["e3e2","g6g3"]}},{"problemid":1361,"first":"Black to Move","type":"Mate in Two","fen":"8/2r3p1/1k3p2/1p1PpP2/pK2P3/P1R4r/1PR5/8 b - - 0 1","solutions":{"c7c4":["c3c4","h3b3"]}},{"problemid":1362,"first":"Black to Move","type":"Mate in Two","fen":"2r2rk1/5p1p/3p2p1/8/4P1P1/nB1qP2P/P2Q4/3KRR2 b - - 0 1","solutions":{"c8c1":["d1c1","d3b1"]}},{"problemid":1363,"first":"Black to Move","type":"Mate in Two","fen":"r3kb1r/pQpbqppp/8/1B6/3Pn3/2P2n2/PP3PPP/RNB2K1R b kq - 0 1","solutions":{"e4g3":["f2g3","e7e1"]}},{"problemid":1364,"first":"Black to Move","type":"Mate in Two","fen":"2b3k1/ppp2p1p/4p1p1/4P2q/4Bn2/3r4/PPQ2P1P/4R1RK b - - 0 1","solutions":{"h5h2":["h1h2","d3h3"]}},{"problemid":1365,"first":"Black to Move","type":"Mate in Two","fen":"2k4r/pp3ppr/2p1pn2/8/3P1bP1/2PQ2N1/PP2BPP1/R4RK1 b - - 0 1","solutions":{"h7h1":["g3h1","f4h2"]}},{"problemid":1366,"first":"Black to Move","type":"Mate in Two","fen":"8/7k/4b1p1/4q3/6PP/6QK/6B1/6b1 b - - 0 1","solutions":{"e6g4":["g3g4","e5h2"]}},{"problemid":1367,"first":"Black to Move","type":"Mate in Two","fen":"8/Qp4pk/p5b1/5p1p/3B2nP/1P4PK/P1P1r1B1/3r4 b - - 0 1","solutions":{"d1h1":["g2h1","e2h2"]}},{"problemid":1368,"first":"Black to Move","type":"Mate in Two","fen":"1r4k1/Q4ppp/3q4/3P1N2/1P3b2/K5P1/P2B1P1P/2Rb4 b - - 0 1","solutions":{"d6b4":["d2b4","f4c1"]}},{"problemid":1369,"first":"Black to Move","type":"Mate in Two","fen":"8/1Q3pkp/6p1/8/r3r2P/PP4PK/2R2q2/3R4 b - - 0 1","solutions":{"e4h4":["g3h4","a4h4"]}},{"problemid":1370,"first":"Black to Move","type":"Mate in Two","fen":"8/p1pk1ppp/8/1b2q3/8/2P1bP2/PP3nPP/RN2K2R b KQ - 0 1","solutions":{"e3f4":["e1f2","e5e3"],"e5d5":["a2a4","d5d1"],"e5d6":["a2a4","d6d1"]}},{"problemid":1371,"first":"Black to Move","type":"Mate in Two","fen":"2b3rk/5pr1/1p1p1n2/p1pP1q1p/P1P4n/1QP3PP/4RN1K/2B3RB b - - 0 1","solutions":{"f5h3":["f2h3","f6g4"]}},{"problemid":1372,"first":"Black to Move","type":"Mate in Two","fen":"7r/6k1/4bpp1/p2p1q1p/N2b1P2/1Br4P/2P1R1PK/4QR2 b - - 0 1","solutions":{"c3h3":["g2h3","f5h3"]}},{"problemid":1373,"first":"Black to Move","type":"Mate in Two","fen":"r3kb1r/p2p1ppp/1p2p3/7q/2P1N3/1P5n/PB2nPPN/R2Q2RK b kq - 0 1","solutions":{"h3f2":["e4f2","e2g3"]}},{"problemid":1374,"first":"Black to Move","type":"Mate in Two","fen":"5r1k/pp4pp/1br5/8/4Pp1q/2N5/PP4PP/R4R1K b - - 0 1","solutions":{"h4h2":["h1h2","c6h6"]}},{"problemid":1375,"first":"Black to Move","type":"Mate in Two","fen":"7k/p1p3bp/3p4/1p1b3q/3n2p1/6P1/PP1NrN2/1Q1BRRK1 b - - 0 1","solutions":{"h5h1":["f2h1","e2g2"]}},{"problemid":1376,"first":"Black to Move","type":"Mate in Two","fen":"7r/5pk1/Q2pp1p1/p5qp/1p2P3/1P2nPPK/PN1RR2P/2r5 b - - 0 1","solutions":{"g5g4":["f3g4","h5g4"]}},{"problemid":1377,"first":"Black to Move","type":"Mate in Two","fen":"2kr3r/ppqn1pp1/2p1p1p1/2b5/8/5NN1/PPQ2nP1/R3BRK1 b - - 0 1","solutions":{"h8h1":["g3h1","f2h3"]}},{"problemid":1378,"first":"Black to Move","type":"Mate in Two","fen":"r2q1rk1/1pp5/3p2nP/p1nPbp2/2P1p2P/1P2P1P1/P2BQKB1/2N2RR1 b - - 0 1","solutions":{"e5g3":["f2g3","d8h4"]}},{"problemid":1379,"first":"Black to Move","type":"Mate in Two","fen":"3rk2r/ppp2ppp/2b5/2b1P1Q1/8/2P5/PP3RPP/RNBq2NK b - - 0 1","solutions":{"d1g1":["h1g1","d8d1"]}},{"problemid":1380,"first":"Black to Move","type":"Mate in Two","fen":"2kr1r2/8/1p2p1pb/p1p1Q2p/8/qPP2P1P/P1K5/1B1R3R b - - 0 1","solutions":{"a3c1":["d1c1","d8d2"]}},{"problemid":1381,"first":"Black to Move","type":"Mate in Two","fen":"4R3/6kp/1b4p1/3Q1nN1/3q1Bn1/1B3P1P/8/r3R2K b - - 0 1","solutions":{"d4g1":["e1g1","a1g1"]}},{"problemid":1382,"first":"Black to Move","type":"Mate in Two","fen":"7k/1b4p1/3b4/8/8/5rPq/2Q2P1P/3BRRK1 b - - 0 1","solutions":{"h3g2":["g1g2","f3g3"]}},{"problemid":1383,"first":"Black to Move","type":"Mate in Two","fen":"4r2k/ppp3pp/8/1PPb1p2/3P1P1b/P1Q2p1P/7R/R4KBq b - - 0 1","solutions":{"h1g2":["h2g2","f3g2"]}},{"problemid":1384,"first":"Black to Move","type":"Mate in Two","fen":"6rk/1p5p/p4R1K/2Q2pB1/2P2P1P/1P6/P5q1/7r b - - 0 1","solutions":{"g2g5":["f4g5","h1h4"]}},{"problemid":1385,"first":"Black to Move","type":"Mate in Two","fen":"1k5r/1Pp3p1/5pqp/7R/5BPK/3r3P/1Q6/R7 b - - 0 1","solutions":{"g6g5":["f4g5","h6g5"]}},{"problemid":1386,"first":"Black to Move","type":"Mate in Two","fen":"r4Nk1/1p2pp1p/2np2p1/p2N4/P2qPPn1/2bB4/2P1K1PP/R2Q1R2 b - - 0 1","solutions":{"d4e3":["d5e3","c6d4"]}},{"problemid":1387,"first":"Black to Move","type":"Mate in Two","fen":"2k5/1pp2Q1b/8/2R5/3pp1p1/1PP1q1P1/2KPB3/7r b - - 0 1","solutions":{"e3d2":["c2d2","e4e3"]}},{"problemid":1388,"first":"Black to Move","type":"Mate in Two","fen":"5r2/1pp3kr/p2P2p1/4p1K1/2P1N1P1/4Q3/PP3P1n/R4R2 b - - 0 1","solutions":{"f8f5":["g4f5","h7h5"]}},{"problemid":1389,"first":"Black to Move","type":"Mate in Two","fen":"6k1/pRQ2pp1/2p4p/8/8/p7/PPPr3P/1K1n4 b - - 0 1","solutions":{"d1c3":["b2c3","d2d1"]}},{"problemid":1390,"first":"Black to Move","type":"Mate in Two","fen":"k5r1/8/1pqB3p/p2nPQ2/3P3P/7K/3P2N1/8 b - - 0 1","solutions":{"d5f4":["g2f4","c6h1"]}},{"problemid":1391,"first":"Black to Move","type":"Mate in Two","fen":"3Q4/2p5/1p1p4/p1n1p2n/P6N/BPP1PP2/5K1k/5b2 b - - 0 1","solutions":{"c5d3":["f2f1","h5g3"]}},{"problemid":1392,"first":"Black to Move","type":"Mate in Two","fen":"r3r1k1/pp3p1p/1q1p2P1/2p5/2Pb4/8/PnQB1P2/2KR3R b - - 0 1","solutions":{"b2d3":["c2d3","b6b2"]}},{"problemid":1393,"first":"Black to Move","type":"Mate in Two","fen":"8/R4Qpk/p1b5/1p1r4/4q3/P3N3/1P3PPP/6K1 b - - 0 1","solutions":{"d5d1":["e3d1","e4g2"]}},{"problemid":1394,"first":"Black to Move","type":"Mate in Two","fen":"5q2/p4p1k/2RQ2p1/3P2K1/1P3PPp/5r1P/8/8 b - - 0 1","solutions":{"f7f6":["d6f6","f8h6"]}},{"problemid":1395,"first":"Black to Move","type":"Mate in Two","fen":"7r/1pp2pk1/3p1bp1/3P1P2/1PP3K1/5RP1/2Q3Bq/8 b - - 0 1","solutions":{"h8h4":["g3h4","h2h4"],"g6g5":["b4b5","h2h5"]}},{"problemid":1396,"first":"Black to Move","type":"Mate in Two","fen":"5k2/pp2R3/8/5Np1/5r2/2P2qPK/PPQ4P/R7 b - - 0 1","solutions":{"f4h4":["f5h4","g5g4"]}},{"problemid":1397,"first":"Black to Move","type":"Mate in Two","fen":"r6q/ppp1nkb1/3pN3/1P1Pp3/P2P1pn1/B4QP1/4P1Br/1R3RK1 b - - 0 1","solutions":{"h2h1":["g2h1","h8h2"]}},{"problemid":1398,"first":"Black to Move","type":"Mate in Two","fen":"2k3r1/1p3pqp/2p1p2p/PP1pP3/3P4/3B1N2/3Q1PrP/2R2R1K b - - 0 1","solutions":{"g2h2":["f3h2","g7g2"]}},{"problemid":1399,"first":"Black to Move","type":"Mate in Two","fen":"3r2k1/2p2ppp/8/2R5/2R2B2/5qP1/4r2P/5QK1 b - - 0 1","solutions":{"d8d1":["f1d1","f3g2"]}},{"problemid":1400,"first":"Black to Move","type":"Mate in Two","fen":"1r4k1/3nqpp1/p1Q4p/B2p3n/3P2P1/2pBPP1K/1r5P/R3R3 b - - 0 1","solutions":{"e7h4":["h3h4","b2h2"]}}]