[{"problemid":1701,"first":"White to Move","type":"Mate in Two","fen":"8/8/8/8/8/3n1N2/8/3Q1K1k w - - 0 1","solutions":{"d1b1":["d3e1","b1h7"]}},{"problemid":1702,"first":"White to Move","type":"Mate in Two","fen":"8/5b1k/7p/8/7K/8/1B6/Q7 w - - 0 1","solutions":{"b2h8":["h7g6","a1b1"]}},{"problemid":1703,"first":"White to Move","type":"Mate in Two","fen":"8/1N1Q4/6N1/3b4/3k4/P7/3K4/8 w - - 0 1","solutions":{"d7d6":["d4c4","d6b4"]}},{"problemid":1704,"first":"White to Move","type":"Mate in Two","fen":"8/8/3q4/4B3/3N4/1Q1K4/p7/k7 w - - 0 1","solutions":{"b3c2":["d6e5","c2c1"]}},{"problemid":1705,"first":"White to Move","type":"Mate in Two","fen":"8/1K6/8/p3p3/k3N3/2Q5/8/8 w - - 0 1","solutions":{"e4d2":["e5e4","c3b3"]}},{"problemid":1706,"first":"White to Move","type":"Mate in Two","fen":"k7/5Q2/3n4/5R2/4R3/8/K7/8 w - - 0 1","solutions":{"f5b5":["d6e4","f7b7"]}},{"problemid":1707,"first":"White to Move","type":"Mate in Two","fen":"8/8/8/1R1b4/R7/2k5/3N4/1B2K3 w - - 0 1","solutions":{"b5b6":["d5h1","a4c4"]}},{"problemid":1708,"first":"White to Move","type":"Mate in Two","fen":"r3k3/3N3K/3Q4/n7/8/8/8/5B2 w - - 0 1","solutions":{"f1h3":["e8f7","d6e6"]}},{"problemid":1709,"first":"White to Move","type":"Mate in Two","fen":"4K1k1/8/6P1/6n1/3B2R1/8/8/8 w - - 0 1","solutions":{"g4h4":["g5f3","h4h8"]}},{"problemid":1710,"first":"White to Move","type":"Mate in Two","fen":"4N3/1Q3N2/8/5k2/1nB5/6K1/8/8 w - - 0 1","solutions":{"b7b6":["b4d5","c4d3"]}},{"problemid":1711,"first":"White to Move","type":"Mate in Two","fen":"4B1Q1/2K3B1/p7/8/1k6/5N2/8/8 w - - 0 1","solutions":{"f3d2":["b4a3","g8b3"]}},{"problemid":1712,"first":"White to Move","type":"Mate in Two","fen":"4K1k1/8/6P1/6n1/3B2B1/8/8/8 w - - 0 1","solutions":{"g4f5":["g5f3","f5e6"]}},{"problemid":1713,"first":"White to Move","type":"Mate in Two","fen":"8/8/8/2N5/3B4/8/kpN1K3/6Q1 w - - 0 1","solutions":{"g1h1":["b2b1q","h1a8"]}},{"problemid":1714,"first":"White to Move","type":"Mate in Two","fen":"8/8/8/2NK4/3B4/8/kpN5/6Q1 w - - 0 1","solutions":{"g1f1":["b2b1q","f1a6"]}},{"problemid":1715,"first":"White to Move","type":"Mate in Two","fen":"8/5p2/8/5QN1/7k/B7/8/7K w - - 0 1","solutions":{"a3c1":["h4g3","f5f4"]}},{"problemid":1716,"first":"White to Move","type":"Mate in Two","fen":"8/8/8/3NP3/1N1kp1Q1/1K6/8/8 w - - 0 1","solutions":{"b4d3":["d4d3","g4d1"]}},{"problemid":1717,"first":"White to Move","type":"Mate in Two","fen":"8/8/K7/2N5/3B4/8/kpN5/6Q1 w - - 0 1","solutions":{"g1e1":["b2b1q","e1a5"]}},{"problemid":1718,"first":"White to Move","type":"Mate in Two","fen":"8/8/8/8/1N6/NpK5/8/kB6 w - - 0 1","solutions":{"b1a2":["b3b2","a3c2"]}},{"problemid":1719,"first":"White to Move","type":"Mate in Two","fen":"8/8/K7/8/p4R2/kp3Q2/2R5/8 w - - 0 1","solutions":{"f4b4":["a3b4","f3f8"]}},{"problemid":1720,"first":"White to Move","type":"Mate in Two","fen":"8/8/5KPk/8/B5P1/8/R3p3/8 w - - 0 1","solutions":{"a4d1":["e2e1q","g4g5"]}},{"problemid":1721,"first":"White to Move","type":"Mate in Two","fen":"8/3p2N1/6Q1/4k3/8/3P4/3B3K/8 w - - 0 1","solutions":{"g7e8":["d7d5","g6f6"]}},{"problemid":1722,"first":"White to Move","type":"Mate in Two","fen":"8/6P1/8/8/8/8/2K5/k7 w - - 0 1","solutions":{"g7g8r":["a1a2","g8a8"]}},{"problemid":1723,"first":"White to Move","type":"Mate in Two","fen":"8/3Q4/8/8/2B5/6K1/8/4k3 w - - 0 1","solutions":{"c4f1":["e1f1","d7d1"]}},{"problemid":1724,"first":"White to Move","type":"Mate in Two","fen":"7k/1R4N1/8/8/7K/6R1/8/7Q w - - 0 1","solutions":{"h1a1":["h8g8","g7e6"]}},{"problemid":1725,"first":"White to Move","type":"Mate in Two","fen":"8/8/6K1/7R/5Pk1/2Q5/3n3b/8 w - - 0 1","solutions":{"h5h3":["d2c4","c3f3"]}},{"problemid":1726,"first":"White to Move","type":"Mate in Two","fen":"8/8/k1K4Q/8/8/8/8/8 w - - 0 1","solutions":{"h6e3":["a6a5","e3a3"]}},{"problemid":1727,"first":"White to Move","type":"Mate in Two","fen":"8/1PBP4/2kN4/5P2/3K4/8/8/8 w - - 0 1","solutions":{"d7d8b":["c6d7","b7b8n"]}},{"problemid":1728,"first":"White to Move","type":"Mate in Two","fen":"8/8/8/3K4/8/5nP1/5Q1b/5N1k w - - 0 1","solutions":{"d5d6":["h2g1","f2f3"]}},{"problemid":1729,"first":"White to Move","type":"Mate in Two","fen":"8/pp6/k7/8/1K6/2R5/3R4/8 w - - 0 1","solutions":{"d2d7":["b7b6","c3a3"]}},{"problemid":1730,"first":"White to Move","type":"Mate in Two","fen":"5k1K/4NP1P/5Q2/8/5n2/8/8/8 w - - 0 1","solutions":{"f6f5":["f4e2","e7g6"]}},{"problemid":1731,"first":"White to Move","type":"Mate in Two","fen":"8/8/2K5/kpN5/8/N1P5/8/8 w - - 0 1","solutions":{"a3c2":["b5b4","c3b4"]}},{"problemid":1732,"first":"White to Move","type":"Mate in Two","fen":"n1N5/1R6/k1nN4/8/K7/8/8/8 w - - 0 1","solutions":{"b7b5":["c6d4","b5a5"]}},{"problemid":1733,"first":"White to Move","type":"Mate in Two","fen":"k7/pq1N4/3R3K/8/8/8/6B1/8 w - - 0 1","solutions":{}},{"problemid":1734,"first":"White to Move","type":"Mate in Two","fen":"8/5p2/5Q2/1B6/4k3/7p/8/1K4B1 w - - 0 1","solutions":{"g1h2":["e4e3","f6f4"]}},{"problemid":1735,"first":"White to Move","type":"Mate in Two","fen":"8/2K5/8/k1Nb4/B2N4/2P5/8/8 w - - 0 1","solutions":{"a4b5":["d5h1","c5b3"]}},{"problemid":1736,"first":"White to Move","type":"Mate in Two","fen":"K3Nk2/PP2p3/4Q3/8/8/8/8/8 w - - 0 1","solutions":{"b7b8n":["f8e8","e6g8"]}},{"problemid":1737,"first":"White to Move","type":"Mate in Two","fen":"1B6/8/pp1N4/k7/8/1PK5/8/8 w - - 0 1","solutions":{"b8a7":["b6b5","d6b7"]}},{"problemid":1738,"first":"White to Move","type":"Mate in Two","fen":"1N6/2Q5/8/3k4/1n6/1p3K2/1B6/8 w - - 0 1","solutions":{"f3e2":["b4d3","c7c6"]}},{"problemid":1739,"first":"White to Move","type":"Mate in Two","fen":"2N5/Nk6/4K3/8/3Q4/8/8/8 w - - 0 1","solutions":{"a7c6":["b7c6","d4b6"]}},{"problemid":1740,"first":"White to Move","type":"Mate in Two","fen":"k7/1R6/nK6/8/8/8/8/8 w - - 0 1","solutions":{"b7d7":["a6b8","d7a7"]}},{"problemid":1741,"first":"White to Move","type":"Mate in Two","fen":"8/k3P3/8/K7/4Q3/8/8/8 w - - 0 1","solutions":{"e4h7":["a7b7","e7e8q"]}},{"problemid":1742,"first":"White to Move","type":"Mate in Two","fen":"8/1k6/8/K3Q3/8/8/8/6B1 w - - 0 1","solutions":{"g1h2":["b7c6","e5b5"]}},{"problemid":1743,"first":"White to Move","type":"Mate in Two","fen":"8/8/8/3K2B1/4pN2/8/3k2P1/1Q6 w - - 0 1","solutions":{"g5h4":["e4e3","h4e1"]}},{"problemid":1744,"first":"White to Move","type":"Mate in Two","fen":"5K2/3p3R/4k1N1/8/6n1/3Q4/8/8 w - - 0 1","solutions":{"h7f7":["g4e5","g6f4"]}},{"problemid":1745,"first":"White to Move","type":"Mate in Two","fen":"5K2/3p1R2/4k3/8/6n1/3Q4/5P2/8 w - - 0 1","solutions":{"f2f4":["g4e5","f4f5"]}},{"problemid":1746,"first":"White to Move","type":"Mate in Two","fen":"8/1B2pK2/1B2Q3/8/8/6kp/8/8 w - - 0 1","solutions":{"b7c8":["h3h2","e6g4"]}},{"problemid":1747,"first":"White to Move","type":"Mate in Two","fen":"8/8/8/8/8/8/kPP5/1nQ1K2R w - - 0 1","solutions":{"e1f2":["b1d2","c1a1"]}},{"problemid":1748,"first":"White to Move","type":"Mate in Two","fen":"4K3/8/5p2/5QNk/8/8/7P/8 w - - 0 1","solutions":{"e8f7":["h5h6","f5g6"]}},{"problemid":1749,"first":"White to Move","type":"Mate in Two","fen":"1K3Q2/3k4/8/8/1PP1P1P1/8/8/8 w - - 0 1","solutions":{"e4e5":["d7c6","f8d6"]}},{"problemid":1750,"first":"White to Move","type":"Mate in Two","fen":"1K3Q2/3k4/6P1/8/1PP1P3/8/8/8 w - - 0 1","solutions":{"c4c5":["d7c6","f8e8"]}},{"problemid":1751,"first":"White to Move","type":"Mate in Two","fen":"8/8/8/5R2/8/2KPkB1b/8/5R2 w - - 0 1","solutions":{"f3d1":["h3f5","f1f3"]}},{"problemid":1752,"first":"White to Move","type":"Mate in Two","fen":"kq6/p7/2K5/7R/8/8/8/Q7 w - - 0 1","solutions":{"h5h8":["b8e8","h8e8"]}},{"problemid":1753,"first":"White to Move","type":"Mate in Two","fen":"8/K7/8/1p6/nk5B/3R4/Q7/8 w - - 0 1","solutions":{"d3d5":["a4c3","h4e7"]}},{"problemid":1754,"first":"White to Move","type":"Mate in Two","fen":"8/3KN3/8/4k3/5p2/5Q1R/8/8 w - - 0 1","solutions":{"h3g3":["f4g3","e7c6"]}},{"problemid":1755,"first":"White to Move","type":"Mate in Two","fen":"8/Q7/6kp/3P4/5P2/6NK/8/8 w - - 0 1","solutions":{"g3h5":["g6h5","a7f7"]}},{"problemid":1756,"first":"White to Move","type":"Mate in Two","fen":"8/1pBN4/8/R7/1k6/3K4/2P5/8 w - - 0 1","solutions":{"d7b8":["b7b6","b8c6"]}},{"problemid":1757,"first":"White to Move","type":"Mate in Two","fen":"8/8/2K5/B7/8/2Pkb3/6Q1/4R3 w - - 0 1","solutions":{"c3c4":["e3d2","g2e4"]}},{"problemid":1758,"first":"White to Move","type":"Mate in Two","fen":"8/8/8/6B1/2Q5/1K6/2p5/1k2n3 w - - 0 1","solutions":{"b3a3":["e1d3","c4a2"]}},{"problemid":1759,"first":"White to Move","type":"Mate in Two","fen":"8/KNkp4/2p5/8/2Q5/8/4B3/8 w - - 0 1","solutions":{"e2g4":["c6c5","c4c5"]}},{"problemid":1760,"first":"White to Move","type":"Mate in Two","fen":"8/4p3/5p2/5k1K/2Q1Nb2/8/8/8 w - - 0 1","solutions":{"e4c3":["e7e6","c4e4"]}},{"problemid":1761,"first":"White to Move","type":"Mate in Two","fen":"4Q3/2k1P3/P4K2/8/8/8/8/8 w - - 0 1","solutions":{"e8b5":["c7d6","e7e8n"]}},{"problemid":1762,"first":"White to Move","type":"Mate in Two","fen":"8/8/2KR4/2ppk3/2r5/5Q2/8/8 w - - 0 1","solutions":{"c6d7":["c4d4","d6e6"]}},{"problemid":1763,"first":"White to Move","type":"Mate in Two","fen":"8/5Bkp/7N/8/3K4/6B1/8/7R w - - 0 1","solutions":{"h1g1":["g7h6","g3f4"]}},{"problemid":1764,"first":"White to Move","type":"Mate in Two","fen":"8/6K1/6p1/6r1/5QPk/8/6P1/8 w - - 0 1","solutions":{"g7h6":["g5a5","g4g5"]}},{"problemid":1765,"first":"White to Move","type":"Mate in Two","fen":"8/8/8/7p/5Kpk/8/8/1B4N1 w - - 0 1","solutions":{"b1f5":["g4g3","g1f3"]}},{"problemid":1766,"first":"White to Move","type":"Mate in Two","fen":"8/8/8/7p/5Kpk/8/8/1N4N1 w - - 0 1","solutions":{"b1d2":["g4g3","d2f3"]}},{"problemid":1767,"first":"White to Move","type":"Mate in Two","fen":"8/8/8/7p/5Kpk/8/8/1R4N1 w - - 0 1","solutions":{"b1b4":["g4g3","f4f5"]}},{"problemid":1768,"first":"White to Move","type":"Mate in Two","fen":"3K4/8/3kp3/3P4/3Q4/4P3/8/8 w - - 0 1","solutions":{"e3e4":["e6d5","d4d5"]}},{"problemid":1769,"first":"White to Move","type":"Mate in Two","fen":"3K4/8/3kp3/3P4/3Q4/5P2/8/8 w - - 0 1","solutions":{"f3f4":["e6d5","d4b6"]}},{"problemid":1770,"first":"White to Move","type":"Mate in Two","fen":"3K4/8/3kp3/3P4/3Q4/1P6/8/8 w - - 0 1","solutions":{"b3b4":["e6d5","d4f6"]}},{"problemid":1771,"first":"White to Move","type":"Mate in Two","fen":"8/8/8/3BP3/8/1P6/8/kbK4Q w - - 0 1","solutions":{"h1e1":["b1a2","e1c3"]}},{"problemid":1772,"first":"White to Move","type":"Mate in Two","fen":"8/8/8/4Q3/3N2pk/7P/8/7K w - - 0 1","solutions":{"d4e6":["g4g3","e5h8"]}},{"problemid":1773,"first":"White to Move","type":"Mate in Two","fen":"6K1/3pp3/4kP2/2Q5/B7/8/8/8 w - - 0 1","solutions":{"a4c2":["e7f6","c2f5"]}},{"problemid":1774,"first":"White to Move","type":"Mate in Two","fen":"8/3P1PBk/5P2/8/6K1/8/8/8 w - - 0 1","solutions":{"d7d8n":["h7g6","f7f8n"]}},{"problemid":1775,"first":"White to Move","type":"Mate in Two","fen":"8/8/8/1R3N2/n1k2N2/8/8/1R2K3 w - - 0 1","solutions":{"b5b7":["c4c3","b1c1"]}},{"problemid":1776,"first":"White to Move","type":"Mate in Two","fen":"8/P1p2K2/3k4/8/2Q5/4P3/8/8 w - - 0 1","solutions":{"a7a8n":["c7c6","c4d4"]}},{"problemid":1777,"first":"White to Move","type":"Mate in Two","fen":"1k1nn3/R2Q4/6K1/8/8/8/8/8 w - - 0 1","solutions":{"d7e7":["d8c6","e7b7"]}},{"problemid":1778,"first":"White to Move","type":"Mate in Two","fen":"8/4kP1R/4P3/3KB3/3P4/8/8/8 w - - 0 1","solutions":{"d5e4":["e7e6","f7f8n"]}},{"problemid":1779,"first":"White to Move","type":"Mate in Two","fen":"8/6pk/7p/3B4/4K3/2BQ4/8/8 w - - 0 1","solutions":{"d3h3":["h7g6","h3f5"]}},{"problemid":1780,"first":"White to Move","type":"Mate in Two","fen":"8/4R3/1Q6/3kb3/N7/7K/2P5/8 w - - 0 1","solutions":{"b6e3":["e5d6","e3e4"]}},{"problemid":1781,"first":"White to Move","type":"Mate in Two","fen":"8/7Q/8/8/8/8/R4Np1/4K1k1 w - - 0 1","solutions":{"f2h1":["g2h1q","h7a7"]}},{"problemid":1782,"first":"White to Move","type":"Mate in Two","fen":"K7/8/8/n7/8/4N3/R3P2R/4k3 w - - 0 1","solutions":{"e3g4":["a5b3","h2h1"]}},{"problemid":1783,"first":"White to Move","type":"Mate in Two","fen":"K7/8/8/7n/8/4N3/R3P2R/4k3 w - - 0 1","solutions":{"e3c4":["h5g3","a2a1"]}},{"problemid":1784,"first":"White to Move","type":"Mate in Two","fen":"5K2/8/8/8/8/5Q1b/2R1B2r/4k3 w - - 0 1","solutions":{"f8e7":["h3g2","f3g3"]}},{"problemid":1785,"first":"White to Move","type":"Mate in Two","fen":"8/8/3pp3/1p1k4/8/2R1K3/8/2Q5 w - - 0 1","solutions":{"c1a1":["d5e5","c3c5"]}},{"problemid":1786,"first":"White to Move","type":"Mate in Two","fen":"8/3K4/2N5/2pkp3/8/8/8/3B2Q1 w - - 0 1","solutions":{"g1g3":["d5c4","g3b3"]}},{"problemid":1787,"first":"White to Move","type":"Mate in Two","fen":"8/8/3B4/Q7/8/2P1N3/3k4/5BK1 w - - 0 1","solutions":{"a5a4":["d2e3","a4f4"]}},{"problemid":1788,"first":"White to Move","type":"Mate in Two","fen":"4kr2/2K2n2/6Q1/3b4/8/B7/8/8 w - - 0 1","solutions":{"g6f5":["f8h8","f5d7"]}},{"problemid":1789,"first":"White to Move","type":"Mate in Two","fen":"3qk3/3N3Q/4N3/5P2/8/8/8/5K2 w - - 0 1","solutions":{"f5f6":["d8a5","h7e7"]}},{"problemid":1790,"first":"White to Move","type":"Mate in Two","fen":"4b2K/6p1/3R1p1k/5Q2/8/8/8/8 w - - 0 1","solutions":{"d6d5":["g7g6","f5h3"]}},{"problemid":1791,"first":"White to Move","type":"Mate in Two","fen":"8/8/8/8/5Q2/5p1k/5p1P/5K1n w - - 0 1","solutions":{"f4g5":["h3h2","g5h4"]}},{"problemid":1792,"first":"White to Move","type":"Mate in Two","fen":"8/8/4N3/N7/8/8/1Pk2P2/Q3K3 w - - 0 1","solutions":{"e6g5":["c2d3","a1d1"]}},{"problemid":1793,"first":"White to Move","type":"Mate in Two","fen":"8/3P1k1B/3K3P/8/4N3/8/8/8 w - - 0 1","solutions":{"e4g5":["f7f6","d7d8q"]}},{"problemid":1794,"first":"White to Move","type":"Mate in Two","fen":"8/8/p2R4/K1k5/3R4/3p4/8/5B2 w - - 0 1","solutions":{"d4d3":["c5c4","d6c6"]}},{"problemid":1795,"first":"White to Move","type":"Mate in Two","fen":"8/8/8/8/8/3p4/3R3p/2k1K2R w - - 0 1","solutions":{"h1h2":["c1b1","d2d1"]}},{"problemid":1796,"first":"White to Move","type":"Mate in Two","fen":"8/1N6/8/2K5/2P5/k7/1R6/2B5 w - - 0 1","solutions":{"b7a5":["a3a4","b2a2"]}},{"problemid":1797,"first":"White to Move","type":"Mate in Two","fen":"8/8/8/6B1/3KN1k1/2Q3P1/6R1/8 w - - 0 1","solutions":{"c3c6":["g4f3","e4f6"]}},{"problemid":1798,"first":"White to Move","type":"Mate in Two","fen":"8/8/8/8/3KN1k1/2Q3P1/B5R1/8 w - - 0 1","solutions":{"c3d2":["g4h3","a2e6"]}},{"problemid":1799,"first":"White to Move","type":"Mate in Two","fen":"4n3/8/1BPk4/1P3Q2/K7/8/8/8 w - - 0 1","solutions":{"c6c7":["d6e7","c7c8n"]}},{"problemid":1800,"first":"White to Move","type":"Mate in Two","fen":"8/8/4Q3/K1k5/2N1b3/2n1P3/8/8 w - - 0 1","solutions":{"c4e5":["c3b1","e5d7"]}}]